opens/__init__.py
opens/o.py
opens/opens.py
opens-1.3.1.dist-info/METADATA
opens-1.3.1.dist-info/WHEEL
opens-1.3.1.dist-info/entry_points.txt
opens-1.3.1.dist-info/RECORD
